farmerchat_prompts/__init__.py
farmerchat_prompts/manager.py
farmerchat_prompts/models.py
farmerchat_prompts/prompts/__init__.py
farmerchat_prompts/prompts/crop_advisory/__init__.py
farmerchat_prompts/prompts/crop_advisory/gemma.py
farmerchat_prompts/prompts/crop_advisory/llama.py
farmerchat_prompts/prompts/crop_advisory/openai.py
farmerchat_prompts/prompts/prompt_evals/__init__.py
farmerchat_prompts/prompts/prompt_evals/gemma.py
farmerchat_prompts/prompts/prompt_evals/llama.py
farmerchat_prompts/prompts/prompt_evals/openai.py
farmerchat_prompts-0.1.1.dist-info/licenses/LICENSE
tests/__init__.py
tests/test_manager.py
farmerchat_prompts-0.1.1.dist-info/METADATA
farmerchat_prompts-0.1.1.dist-info/WHEEL
farmerchat_prompts-0.1.1.dist-info/top_level.txt
farmerchat_prompts-0.1.1.dist-info/RECORD
